{
  "project_info": {
    "project_number": "729687772292",
    "firebase_url": "https://rockin-app.firebaseio.com",
    "project_id": "rockin-app",
    "storage_bucket": "rockin-app.appspot.com"
  },
  "client": [
    {
      "client_info": {
        "mobilesdk_app_id": "1:729687772292:android:0066638c9ad835681006d1",
        "android_client_info": {
          "package_name": "ch.heigvd.pro.b04.android"
        }
      },
      "oauth_client": [
        {
          "client_id": "729687772292-pkno0jvfskom9524fs1v13l15qk7f0qe.apps.googleusercontent.com",
          "client_type": 3
        }
      ],
      "api_key": [
        {
          "current_key": "AIzaSyC8lsRXM25yvPzUWxRtJOnMi3xuyW4hPg8"
        }
      ],
      "services": {
        "appinvite_service": {
          "other_platform_oauth_client": [
            {
              "client_id": "729687772292-pkno0jvfskom9524fs1v13l15qk7f0qe.apps.googleusercontent.com",
              "client_type": 3
            }
          ]
        }
      }
    }
  ],
  "configuration_version": "1"
}